CONTRIBUTING.rst
MANIFEST.in
README.rst
setup.cfg
setup.py
wellspring/__init__.py
wellspring/wellspring.py
wellspring.egg-info/PKG-INFO
wellspring.egg-info/SOURCES.txt
wellspring.egg-info/dependency_links.txt
wellspring.egg-info/not-zip-safe
wellspring.egg-info/requires.txt
wellspring.egg-info/top_level.txt