Metadata-Version: 1.0
Name: wellspring
Version: 0.1.9
Summary: Custom pyspark package to work with Databricks
Home-page: https://pypi.org/project/wellspring/
Author: Tarun Rana
Author-email: tarun.rana@henkel.com
License: MIT
Platform: UNKNOWN
